COPYRIGHT
LICENSE
MANIFEST.in
README.rst
setup.py
tryton_filestore_minio.py
doc/acknowledgments.rst
doc/conf.py
doc/configuration.rst
doc/index.rst
doc/installation.rst
doc/license.rst
doc/support.rst
tryton_filestore_minio.egg-info/PKG-INFO
tryton_filestore_minio.egg-info/SOURCES.txt
tryton_filestore_minio.egg-info/dependency_links.txt
tryton_filestore_minio.egg-info/not-zip-safe
tryton_filestore_minio.egg-info/requires.txt
tryton_filestore_minio.egg-info/top_level.txt